basiccalls-2.2.9.2.dist-info/licenses/LICENSE
pytgcalls/__init__.py
pytgcalls/__version__.py
pytgcalls/chat_lock.py
pytgcalls/environment.py
pytgcalls/exceptions.py
pytgcalls/ffmpeg.py
pytgcalls/filters.py
pytgcalls/list_to_cmd.py
pytgcalls/mtproto_required.py
pytgcalls/mutex.py
pytgcalls/pytgcalls.py
pytgcalls/pytgcalls_session.py
pytgcalls/scaffold.py
pytgcalls/statictypes.py
pytgcalls/sync.py
pytgcalls/version_manager.py
pytgcalls/wait_counter_lock.py
pytgcalls/ytdlp.py
pytgcalls/custom_api/__init__.py
pytgcalls/custom_api/custom_api.py
pytgcalls/handlers/__init__.py
pytgcalls/handlers/handlers_holder.py
pytgcalls/media_devices/__init__.py
pytgcalls/media_devices/device_info.py
pytgcalls/media_devices/input_device.py
pytgcalls/media_devices/media_devices.py
pytgcalls/media_devices/screen_device.py
pytgcalls/media_devices/speaker_device.py
pytgcalls/methods/__init__.py
pytgcalls/methods/calls/__init__.py
pytgcalls/methods/calls/change_volume_call.py
pytgcalls/methods/calls/get_participants.py
pytgcalls/methods/calls/leave_call.py
pytgcalls/methods/decorators/__init__.py
pytgcalls/methods/decorators/on_update.py
pytgcalls/methods/internal/__init__.py
pytgcalls/methods/internal/clear_cache.py
pytgcalls/methods/internal/clear_call.py
pytgcalls/methods/internal/connect_call.py
pytgcalls/methods/internal/emit_sig_data.py
pytgcalls/methods/internal/handle_connection_changed.py
pytgcalls/methods/internal/handle_mtproto_updates.py
pytgcalls/methods/internal/handle_stream_ended.py
pytgcalls/methods/internal/handle_stream_frame.py
pytgcalls/methods/internal/join_presentation.py
pytgcalls/methods/internal/log_retries.py
pytgcalls/methods/internal/request_broadcast_part.py
pytgcalls/methods/internal/request_broadcast_timestamp.py
pytgcalls/methods/internal/switch_connection.py
pytgcalls/methods/internal/update_sources.py
pytgcalls/methods/internal/update_status.py
pytgcalls/methods/stream/__init__.py
pytgcalls/methods/stream/mute.py
pytgcalls/methods/stream/pause.py
pytgcalls/methods/stream/play.py
basiccalls-2.2.9.2.dist-info/METADATA
basiccalls-2.2.9.2.dist-info/WHEEL
basiccalls-2.2.9.2.dist-info/top_level.txt
basiccalls-2.2.9.2.dist-info/RECORD
