Metadata-Version: 2.4
Name: basiccalls
Version: 2.2.9.2
Summary: Fork of py-tgcalls: Enhanced async client API for Telegram Calls with Kurigram compatibility and extended features.
Author-email: Yakup Kaya <y4kupkaya@gmail.com>
Project-URL: Homepage, https://yakupkaya.me
Project-URL: Repository, https://github.com/y4kupkaya/basiccalls.git
Project-URL: Documentation, https://github.com/y4kupkaya/basiccalls/blob/main/README.md
Project-URL: Changelog, https://github.com/y4kupkaya/basiccalls/releases
Keywords: audio,python,library,video,telegram,stream,ffmpeg,cpp,webrtc,voice-chat,voip,group-chat,video-calls,calls,video-chat,pytgcalls,ntgcalls,tgcalls,py-tgcalls,basiccalls,kurigram,pyrogram,telethon,hydrogram
Classifier: Operating System :: OS Independent
Classifier: Programming Language :: Python :: 3
Classifier: Programming Language :: Python :: 3 :: Only
Classifier: Programming Language :: Python :: 3.9
Classifier: Programming Language :: Python :: 3.10
Classifier: Programming Language :: Python :: 3.11
Classifier: Programming Language :: Python :: 3.12
Classifier: Programming Language :: Python :: 3.13
Classifier: Programming Language :: Python :: 3.14
Requires-Python: >=3.9
License-File: LICENSE
Requires-Dist: aiohttp>=3.9.3
Requires-Dist: ntgcalls
Requires-Dist: deprecation
Provides-Extra: pyrogram
Requires-Dist: pyrogram>=1.2.20; extra == "pyrogram"
Provides-Extra: telethon
Requires-Dist: telethon>=1.24.0; extra == "telethon"
Provides-Extra: hydrogram
Requires-Dist: hydrogram>=0.1.4; extra == "hydrogram"
Dynamic: license-file
